licencia/__init__.py
licencia/app.py
licencia/commands.py
licencia/core.py
licencia-0.1.1.dist-info/entry_points.txt
licencia-0.1.1.dist-info/LICENSE
licencia-0.1.1.dist-info/WHEEL
licencia-0.1.1.dist-info/METADATA
licencia-0.1.1.dist-info/RECORD
